{
  "indexes": [
    {
      "collectionGroup": "tasks",
      "queryScope": "COLLECTION",
      "fields": [
        {
          "fieldPath": "type",
          "order": "ASCENDING"
        },
        {
          "fieldPath": "status",
          "order": "ASCENDING"
        },
        {
          "fieldPath": "createdAt",
          "order": "DESCENDING"
        }
      ]
    },
    {
      "collectionGroup": "tasks",
      "queryScope": "COLLECTION",
      "fields": [
        {
          "fieldPath": "type",
          "order": "ASCENDING"
        },
        {
          "fieldPath": "weeklyDayOfWeek",
          "order": "ASCENDING"
        },
        {
          "fieldPath": "status",
          "order": "ASCENDING"
        }
      ]
    },
    {
      "collectionGroup": "overdueReports",
      "queryScope": "COLLECTION",
      "fields": [
        {
          "fieldPath": "processedAt",
          "order": "DESCENDING"
        }
      ]
    }
  ],
  "fieldOverrides": []
}